pyloadprojects/__init__.py
pyloadprojects/data.py
pyloadprojects/plp.py
pyloadprojects-1.0.dist-info/LICENSE
pyloadprojects-1.0.dist-info/METADATA
pyloadprojects-1.0.dist-info/WHEEL
pyloadprojects-1.0.dist-info/top_level.txt
pyloadprojects-1.0.dist-info/RECORD
