Metadata-Version: 2.1
Name: pyloadprojects
Version: 1.0
Summary: A simple installer of the program.
Home-page: https://github.com/AnKei-2022/PyLoadProjects
Author: AnKei
Keywords: python
Classifier: Programming Language :: Python :: 3.11
Classifier: License :: OSI Approved :: MIT License
Classifier: Operating System :: OS Independent
Requires-Python: >=3.8
License-File: LICENSE
Requires-Dist: elevate (>=0.1.3)
Requires-Dist: pywin32
